ASUllm/__init__.py
ASUllm/api.py
ASUllm/model_config.py
ASUllm/models.py
ASUllm-0.0.5.dist-info/LICENSE
ASUllm-0.0.5.dist-info/METADATA
ASUllm-0.0.5.dist-info/WHEEL
ASUllm-0.0.5.dist-info/top_level.txt
ASUllm-0.0.5.dist-info/RECORD
