Metadata-Version: 2.1
Name: ASUllm
Version: 0.0.5
Summary: A simple python package to facilitate connection to ASU LLM API
Author-email: Stella Wenxing Liu <stellawenxingliu@gmail.com>
Project-URL: Homepage, https://github.com/ASU/aiml-ssmdv-student-support-ml-data-visualization
Project-URL: Issues, https://github.com/ASU/aiml-ssmdv-student-support-ml-data-visualization/issues
Classifier: Programming Language :: Python :: 3
Classifier: License :: OSI Approved :: MIT License
Classifier: Operating System :: OS Independent
Requires-Python: >=3.8
License-File: LICENSE
